ratelimiterx/__init__.py
ratelimiterx/__version__.py
ratelimiterx/ratelimiterx.py
ratelimiterx-0.1.1.dist-info/METADATA
ratelimiterx-0.1.1.dist-info/WHEEL
ratelimiterx-0.1.1.dist-info/top_level.txt
ratelimiterx-0.1.1.dist-info/RECORD
